{"v":5,"entries":{"configure-your-project--docs":{"id":"configure-your-project--docs","title":"Configure your project","name":"Docs","importPath":"./src/stories/Configure.mdx","storiesImports":[],"type":"docs","tags":["dev","test","unattached-mdx"]},"data-entry--text-inputs":{"type":"story","id":"data-entry--text-inputs","name":"Text Inputs","title":"Data Entry","importPath":"./src/components/stories/DataEntry.stories.jsx","tags":["dev","test"]},"data-entry--checkboxes":{"type":"story","id":"data-entry--checkboxes","name":"Checkboxes","title":"Data Entry","importPath":"./src/components/stories/DataEntry.stories.jsx","tags":["dev","test"]},"feedback--toast-examples":{"type":"story","id":"feedback--toast-examples","name":"Toast Examples","title":"Feedback","importPath":"./src/components/stories/Feedback.stories.jsx","tags":["dev","test"]},"feedback--modal-example":{"type":"story","id":"feedback--modal-example","name":"Modal Example","title":"Feedback","importPath":"./src/components/stories/Feedback.stories.jsx","tags":["dev","test"]},"typography--headings":{"type":"story","id":"typography--headings","name":"Headings","title":"Typography","importPath":"./src/components/stories/Typography.stories.jsx","tags":["dev","test"]},"typography--body-text":{"type":"story","id":"typography--body-text","name":"Body Text","title":"Typography","importPath":"./src/components/stories/Typography.stories.jsx","tags":["dev","test"]},"example-button--docs":{"id":"example-button--docs","title":"Example/Button","name":"Docs","importPath":"./src/stories/Button.stories.js","type":"docs","tags":["dev","test","autodocs"],"storiesImports":[]},"example-button--primary":{"type":"story","id":"example-button--primary","name":"Primary","title":"Example/Button","importPath":"./src/stories/Button.stories.js","componentPath":"./src/stories/Button.jsx","tags":["dev","test","autodocs"]},"example-button--secondary":{"type":"story","id":"example-button--secondary","name":"Secondary","title":"Example/Button","importPath":"./src/stories/Button.stories.js","componentPath":"./src/stories/Button.jsx","tags":["dev","test","autodocs"]},"example-button--large":{"type":"story","id":"example-button--large","name":"Large","title":"Example/Button","importPath":"./src/stories/Button.stories.js","componentPath":"./src/stories/Button.jsx","tags":["dev","test","autodocs"]},"example-button--small":{"type":"story","id":"example-button--small","name":"Small","title":"Example/Button","importPath":"./src/stories/Button.stories.js","componentPath":"./src/stories/Button.jsx","tags":["dev","test","autodocs"]},"example-header--docs":{"id":"example-header--docs","title":"Example/Header","name":"Docs","importPath":"./src/stories/Header.stories.js","type":"docs","tags":["dev","test","autodocs"],"storiesImports":[]},"example-header--logged-in":{"type":"story","id":"example-header--logged-in","name":"Logged In","title":"Example/Header","importPath":"./src/stories/Header.stories.js","componentPath":"./src/stories/Header.jsx","tags":["dev","test","autodocs"]},"example-header--logged-out":{"type":"story","id":"example-header--logged-out","name":"Logged Out","title":"Example/Header","importPath":"./src/stories/Header.stories.js","componentPath":"./src/stories/Header.jsx","tags":["dev","test","autodocs"]},"example-page--logged-out":{"type":"story","id":"example-page--logged-out","name":"Logged Out","title":"Example/Page","importPath":"./src/stories/Page.stories.js","componentPath":"./src/stories/Page.jsx","tags":["dev","test"]},"example-page--logged-in":{"type":"story","id":"example-page--logged-in","name":"Logged In","title":"Example/Page","importPath":"./src/stories/Page.stories.js","componentPath":"./src/stories/Page.jsx","tags":["dev","test","play-fn"]}}}